astraflow/__init__.py
astraflow/core.py
astraflow-0.1.1.dist-info/licenses/LICENSE
astraflow-0.1.1.dist-info/METADATA
astraflow-0.1.1.dist-info/WHEEL
astraflow-0.1.1.dist-info/top_level.txt
astraflow-0.1.1.dist-info/RECORD
