Metadata-Version: 2.4
Name: astraflow
Version: 0.1.1
Summary: Efficient training
Author-email: Haizhong Zheng <hzzheng@umich.edu>
License: MIT
Project-URL: Homepage, https://github.com/Infini-AI-Lab/M2PO
Requires-Python: >=3.10
License-File: LICENSE
Requires-Dist: requests>=2.0
Dynamic: license-file
